leverage/__init__.py
leverage/_internals.py
leverage/_parsing.py
leverage/_utils.py
leverage/conf.py
leverage/container.py
leverage/containers/kubectl.py
leverage/leverage.py
leverage/logger.py
leverage/modules/__init__.py
leverage/modules/auth.py
leverage/modules/aws.py
leverage/modules/credentials.py
leverage/modules/kubectl.py
leverage/modules/project.py
leverage/modules/run.py
leverage/modules/shell.py
leverage/modules/tf.py
leverage/modules/tfautomv.py
leverage/modules/utils.py
leverage/path.py
leverage/tasks.py
leverage-2.1.1.dist-info/LICENSE.txt
leverage-2.1.1.dist-info/METADATA
leverage-2.1.1.dist-info/WHEEL
leverage-2.1.1.dist-info/entry_points.txt
leverage-2.1.1.dist-info/RECORD
