Metadata-Version: 2.1
Name: leverage
Version: 2.1.1
Summary: Binbash Leverage Command-Line tool.
Home-page: https://github.com/binbashar/leverage
License: MIT
Keywords: leverage,binbash
Author: BinBash Inc
Author-email: leverage@binbash.com.ar
Requires-Python: >=3.9,<3.14
Classifier: Development Status :: 5 - Production/Stable
Classifier: Intended Audience :: Developers
Classifier: License :: OSI Approved :: MIT License
Classifier: Programming Language :: Python :: 3
Classifier: Programming Language :: Python :: 3.9
Classifier: Programming Language :: Python :: 3.10
Classifier: Programming Language :: Python :: 3.11
Classifier: Programming Language :: Python :: 3.12
Classifier: Programming Language :: Python :: 3.13
Classifier: Topic :: Software Development :: Build Tools
Requires-Dist: boto3 (==1.33.2)
Requires-Dist: click (==8.0.1)
Requires-Dist: configupdater (==3.2)
Requires-Dist: docker (==6.1.0)
Requires-Dist: dockerpty (==0.4.1)
Requires-Dist: docutils (==0.17.1)
Requires-Dist: jinja2 (==3.0.1)
Requires-Dist: python-hcl2 (==7.3.1)
Requires-Dist: questionary (==1.10.0)
Requires-Dist: requests (==2.31)
Requires-Dist: rich (==14.1.0)
Requires-Dist: ruamel.yaml (==0.17.10)
Requires-Dist: simple-term-menu (==1.6.4)
Requires-Dist: yaenv (==1.5.3post1)
Project-URL: Documentation, https://leverage.binbash.co/
Project-URL: Repository, https://github.com/binbashar/leverage
